{"cameraMode":{"drawMode":0,"name":"Shaded","section":"Shading Mode"},"sceneLighting":true,"audioPlay":false,"sceneViewState":{"m_AlwaysRefresh":false,"showFog":true,"showSkybox":true,"showFlares":true,"showImageEffects":true,"showParticleSystems":true,"showVisualEffectGraphs":true,"m_FxEnabled":true},"in2DMode":false,"pivot":{"x":1750.1011962890625,"y":837.8076171875,"z":822.21923828125},"rotation":{"x":-0.022800641134381295,"y":0.02458823472261429,"z":-0.000560450425837189,"w":-0.9994427561759949},"size":579.653076171875,"orthographic":false}